__init__.py
py_rtx_remix/__init__.py
py_rtx_remix/api_data_types.py
py_rtx_remix/components.py
py_rtx_remix/core.py
py_rtx_remix/example.py
py_rtx_remix/exceptions.py
py_rtx_remix/remixapi.dll
py_rtx_remix/simple_obj_importer.py
py_rtx_remix-0.0.2.dist-info/licenses/LICENSE
py_rtx_remix-0.0.2.dist-info/METADATA
py_rtx_remix-0.0.2.dist-info/WHEEL
py_rtx_remix-0.0.2.dist-info/top_level.txt
py_rtx_remix-0.0.2.dist-info/RECORD
