Metadata-Version: 2.4
Name: py_rtx_remix
Version: 0.0.2
Summary: A Python Wrapper over the Nvidia RTX Remix C API for its Raytracing Engine.
Author-email: "Emanuel Kozerski (E-man)" <emanualkoz.97@gmail.com>
License: MIT License
Project-URL: Homepage, https://github.com/Ekozmaster/py-rtx-remix
Project-URL: Issues, https://github.com/Ekozmaster/py-rtx-remix/issues
Classifier: Programming Language :: Python :: 3
Classifier: Operating System :: Microsoft :: Windows
Requires-Python: >=3.10.11
License-File: LICENSE
Dynamic: license-file
